grappa/__init__.py
grappa/_version.py
grappa/example_module.py
grappa/py.typed
astrograppa-0.1.2a0.dist-info/LICENSE
astrograppa-0.1.2a0.dist-info/METADATA
astrograppa-0.1.2a0.dist-info/WHEEL
astrograppa-0.1.2a0.dist-info/top_level.txt
astrograppa-0.1.2a0.dist-info/RECORD
